aii.py
a2py-0.2.3.dist-info/METADATA
a2py-0.2.3.dist-info/WHEEL
a2py-0.2.3.dist-info/entry_points.txt
a2py-0.2.3.dist-info/licenses/LICENSE
a2py-0.2.3.dist-info/RECORD
