Metadata-Version: 2.4
Name: a2py
Version: 0.2.3
Summary: Multi-modal AI assistant for translation, explanation, coding, writing, and shell automation
Project-URL: Homepage, https://github.com/ttware/aii
Project-URL: Bug Reports, https://github.com/ttware/aii/issues
Project-URL: Source, https://github.com/ttware/aii
Project-URL: Documentation, https://github.com/ttware/aii#readme
Author-email: Dev <dev@ttware.cc>
License: Apache-2.0
License-File: LICENSE
Keywords: ai,assistant,automation,cli,coding,gemini,pydantic-ai,shell,translation
Classifier: Development Status :: 4 - Beta
Classifier: Environment :: Console
Classifier: Intended Audience :: Developers
Classifier: Intended Audience :: System Administrators
Classifier: License :: OSI Approved :: Apache Software License
Classifier: Operating System :: OS Independent
Classifier: Programming Language :: Python :: 3
Classifier: Programming Language :: Python :: 3.10
Classifier: Programming Language :: Python :: 3.11
Classifier: Programming Language :: Python :: 3.12
Classifier: Programming Language :: Python :: 3.13
Classifier: Topic :: Software Development :: Libraries :: Python Modules
Classifier: Topic :: System :: Shells
Classifier: Topic :: Utilities
Classifier: Typing :: Typed
Requires-Python: >=3.10
Requires-Dist: importlib-metadata>=1.0; python_version < '3.8'
Requires-Dist: pydantic-ai[anthropic,openai]>=1.0.6
Requires-Dist: typing-extensions>=4.0.0; python_version < '3.11'
Provides-Extra: dev
Requires-Dist: black; extra == 'dev'
Requires-Dist: isort; extra == 'dev'
Requires-Dist: mypy; extra == 'dev'
Requires-Dist: pytest; extra == 'dev'
Requires-Dist: pytest-cov; extra == 'dev'
Requires-Dist: ruff; extra == 'dev'
Requires-Dist: types-psutil; extra == 'dev'
